paig_common/VERSION
paig_common/__init__.py
paig_common/async_base_rest_http_client.py
paig_common/async_http_transport.py
paig_common/audit_spooler.py
paig_common/config_utils.py
paig_common/constants.py
paig_common/encryption.py
paig_common/file_utils.py
paig_common/http_transport.py
paig_common/lru_cache.py
paig_common/paig_exception.py
paig_common/rbac_manager.py
paig_common/response.py
paig_common-0.0.1.dist-info/METADATA
paig_common-0.0.1.dist-info/WHEEL
paig_common-0.0.1.dist-info/RECORD
