Metadata-Version: 2.3
Name: paig-common
Version: 0.0.1
Summary: PAIG Shield Common Library
Project-URL: Homepage, https://github.com/pypa/paig_common
Project-URL: Bug Tracker, https://github.com/pypa/paig_common/issues
Author-email: Privacera  <support@privacera.com>
License:                                  Apache License
Classifier: License :: Other/Proprietary License
Classifier: Operating System :: OS Independent
Classifier: Programming Language :: Python :: 3
Requires-Python: >=3.8.1
Requires-Dist: cryptography>=41.0.4
Requires-Dist: jproperties>=2.1.1
Requires-Dist: urllib3>=2.0.6
